<?xml version="1.0" encoding="UTF-8"?>
<ti:app xmlns:ti="http://ti.appcelerator.org">
	<id>com.stevenhouse.todo</id>
	<name>To-Do</name>
	<version>1.0</version>
	<publisher>not specified</publisher>
	<url/>
	<description/>
	<copyright>not specified</copyright>
	<icon>appicon.png</icon>
	<fullscreen>false</fullscreen>
	<navbar-hidden>false</navbar-hidden>
	<analytics>true</analytics>
	<guid>d1d85346-deb3-4fa2-ba93-ae7be21cefbb</guid>
	<property name="ti.ui.defaultunit" type="string">dp</property>
	<ios>
		<plist>
			<dict>
                <key>UIBackgroundModes</key>
                <array>
                    <string>fetch</string>
                    <string>remote-notification</string>
                </array>
                <key>UISupportedInterfaceOrientations~iphone</key>
				<array>
					<string>UIInterfaceOrientationPortrait</string>
				</array>
				<key>UISupportedInterfaceOrientations~ipad</key>
				<array>
					<string>UIInterfaceOrientationPortrait</string>
					<string>UIInterfaceOrientationPortraitUpsideDown</string>
					<string>UIInterfaceOrientationLandscapeLeft</string>
					<string>UIInterfaceOrientationLandscapeRight</string>
				</array>
				<key>UIRequiresPersistentWiFi</key>
				<false/>
				<key>UIPrerenderedIcon</key>
				<false/>
				<key>UIStatusBarHidden</key>
				<false/>
				<key>UIStatusBarStyle</key>
				<string>UIStatusBarStyleDefault</string>
			</dict>
		</plist>
	</ios>
    <android xmlns:android="http://schemas.android.com/apk/res/android">
        <tool-api-level>16</tool-api-level>
        <manifest android:installLocation="auto" android:versionCode="1" android:versionName="1" package="com.mkamithkumar.whatstoday" xmlns:android="http://schemas.android.com/apk/res/android">
            <uses-sdk android:minSdkVersion="8" android:targetSdkVersion="11"/>
            <supports-screens android:anyDensity="true"/>
            <application android:debuggable="false" android:icon="@drawable/appicon" android:label="Whats Today" android:name="WhatsTodayApplication" android:theme="@android:style/Theme.DeviceDefault.Light">

                <receiver android:name="bencoding.alarmmanager.AlarmNotificationListener"/>
                <receiver android:name="bencoding.alarmmanager.AlarmServiceListener"/>
                <activity android:configChanges="keyboardHidden|orientation|screenSize"
                          android:alwaysRetainTaskState="true"
                          android:label="Whats Today"
                          android:name=".TodoActivity"
                          android:theme="@style/Theme.Titanium"
                          android:launchMode="singleTop">
                    <intent-filter>
                        <action android:name="android.intent.action.MAIN"/>
                        <category android:name="android.intent.category.LAUNCHER"/>
                    </intent-filter>
                </activity>
                <activity android:configChanges="keyboardHidden|orientation|screenSize" android:name="org.appcelerator.titanium.TiActivity"/>
                <activity android:configChanges="keyboardHidden|orientation|screenSize" android:name="org.appcelerator.titanium.TiTranslucentActivity" android:theme="@android:style/Theme.Translucent"/>
                <activity android:configChanges="keyboardHidden|orientation|screenSize" android:name="org.appcelerator.titanium.TiModalActivity" android:theme="@android:style/Theme.Translucent"/>
                <activity android:configChanges="keyboardHidden|orientation|screenSize" android:name="ti.modules.titanium.ui.TiTabActivity"/>
                <activity android:name="ti.modules.titanium.ui.android.TiPreferencesActivity"/>
                <service android:exported="false" android:name="org.appcelerator.titanium.analytics.TiAnalyticsService"/>

            </application>
            <uses-permission android:name="android.permission.VIBRATE"/>
            <uses-permission android:name="android.permission.ACCESS_NETWORK_STATE"/>
            <uses-permission android:name="android.permission.WRITE_EXTERNAL_STORAGE"/>
            <uses-permission android:name="android.permission.VIBRATE"/>
            <uses-permission android:name="android.permission.WAKE_LOCK"/>
            <uses-permission android:name="android.permission.ACCESS_WIFI_STATE"/>
            <uses-permission android:name="android.permission.INTERNET"/>

            <!-- Use GPS for device location -->
            <uses-permission android:name="android.permission.ACCESS_FINE_LOCATION"/>
            <!-- Use Wi-Fi or mobile connection for device location -->
            <uses-permission android:name="android.permission.ACCESS_COARSE_LOCATION"/>
            <!-- Allow Mock Location -->
            <uses-permission android:name="android.permission.ACCESS_MOCK_LOCATION" />
            <!-- Allows the API to access Google web-based services -->
            <uses-permission android:name="com.google.android.providers.gsf.permission.READ_GSERVICES"/>
            <!-- Specify OpenGL ES 2.0 as a requirement -->
            <uses-feature android:glEsVersion="0x00020000" android:required="true"/>
            <!-- Replace <com.domain.appid> with your application ID -->
            <permission android:name="com.sivci.thefleet.permission.MAPS_RECEIVE" android:protectionLevel="signature"/>
            <uses-permission android:name="com.sivci.thefleet.permission.MAPS_RECEIVE"/>
            <application android:theme="@style/Theme.NoActionBar">
                <!-- Replace "PASTE YOUR GOOGLE MAPS API KEY HERE" with the Google API key you obtained -->
                <meta-data android:name="com.google.android.maps.v2.API_KEY" android:value="AIzaSyC1kuSBYwxo0Iy562fgXLZDVzbdhp9Lnqk"/>
            </application>

        </manifest>
        <services>
            <service type="interval" url="notificationService.js"/>
        </services>
    </android>

	<modules>
        <module platform="android" version="0.2">ti.sq</module>
        <module platform="iphone" version="0.4">ti.sq</module>
        <module platform="ios" version="1.7.10">dk.napp.social</module>
        <module platform="android" version="0.3">yy.tidialogs</module>
        <module platform="ios">crittercism</module>
        <module platform="android">crittercism</module>
        <module platform="android" version="0.1.2">net.iamyellow.tiws</module>
        <module platform="iphone" version="0.5">net.iamyellow.tiws</module>
        <module platform="android" version="0.11">bencoding.alarmmanager</module>
        <module platform="android">ti.map</module>
        <module platform="iphone">ti.map</module>
        <module platform="iphone" version="1.0.0">ti.geocoder</module>
        <module platform="android" version="1.0.0">ti.geocoder</module>
        <module platform="android" version="0.6">bencoding.basicgeo</module>
        <module platform="iphone" version="0.92">bencoding.basicgeo</module>
    </modules>
	<deployment-targets>
		<target device="android">true</target>
		<target device="ipad">true</target>
		<target device="iphone">true</target>
	</deployment-targets>
	<sdk-version>3.5.1.GA</sdk-version>
<plugins><plugin version="1.0">ti.alloy</plugin>
</plugins>
</ti:app>
